senka/__init__.py
senka/plugin_manager.py
senka/senka.py
senka/unknown_transaction.py
senka-0.1.1.dist-info/LICENSE
senka-0.1.1.dist-info/WHEEL
senka-0.1.1.dist-info/METADATA
senka-0.1.1.dist-info/RECORD
